atap_corpus/__init__.py
atap_corpus/_types.py
atap_corpus/corpus/__init__.py
atap_corpus/corpus/base.py
atap_corpus/corpus/corpora.py
atap_corpus/corpus/corpus.py
atap_corpus/interfaces.py
atap_corpus/mixins.py
atap_corpus/parts/__init__.py
atap_corpus/parts/base.py
atap_corpus/parts/dtm.py
atap_corpus/registry.py
atap_corpus/slicer/__init__.py
atap_corpus/slicer/op.py
atap_corpus/slicer/ops.py
atap_corpus/slicer/slicer.py
atap_corpus/utils.py
atap_corpus-0.1.15.dist-info/LICENSE.txt
atap_corpus-0.1.15.dist-info/METADATA
atap_corpus-0.1.15.dist-info/WHEEL
atap_corpus-0.1.15.dist-info/RECORD
