Metadata-Version: 2.1
Name: atap-corpus
Version: 0.1.15
Summary: Corpus mini-framework allowing for memory-efficient slicing and provides a standardised base corpus structure for the collection of ATAP tools. 
Home-page: https://github.com/Australian-Text-Analytics-Platform/atap_corpus
License: MIT
Author: Jack Chan
Author-email: huen.chan@sydney.edu.au
Requires-Python: >=3.10,<3.13
Classifier: License :: OSI Approved :: MIT License
Classifier: Programming Language :: Python :: 3
Classifier: Programming Language :: Python :: 3.10
Classifier: Programming Language :: Python :: 3.11
Classifier: Programming Language :: Python :: 3.12
Provides-Extra: apple
Provides-Extra: viz
Requires-Dist: chardet (>=5.0.0,<6.0.0)
Requires-Dist: colorlog (>=6.7.0,<7.0.0)
Requires-Dist: coolname (>=2.2.0,<3.0.0)
Requires-Dist: ipywidgets (>=8.0) ; extra == "viz"
Requires-Dist: matplotlib (>=3.5.2,<4.0.0) ; extra == "viz"
Requires-Dist: openpyxl (>=3.1.1,<4.0.0)
Requires-Dist: pandas[excel,parquet,performance] (>=2.1)
Requires-Dist: panel (>=1.2.3,<2.0.0) ; extra == "viz"
Requires-Dist: plotly (>=5.11.0,<6.0.0) ; extra == "viz"
Requires-Dist: pyarrow (>=14.0.1)
Requires-Dist: scikit-learn (>=1.1.1)
Requires-Dist: scipy (>=1.11)
Requires-Dist: spacy (>=v3.4.1,<4.0.0)
Requires-Dist: thinc-apple-ops[apple] (>=0.1.0,<0.2.0) ; (sys_platform == "apple") and (extra == "apple")
Requires-Dist: tqdm (>=4.64.0,<5.0.0)
Requires-Dist: urllib3 (>=1.26.18,<2.0.0) ; extra == "apple"
Project-URL: Repository, https://github.com/Australian-Text-Analytics-Platform/atap_corpus
